filewiz/__init__.py
filewiz/__main__.py
filewiz/_watchdog.py
filewiz/directory_scanner.py
filewiz/file_mover.py
filewiz/handler.py
filewiz/readline_util.py
filewiz-1.2.2.dist-info/METADATA
filewiz-1.2.2.dist-info/WHEEL
filewiz-1.2.2.dist-info/entry_points.txt
filewiz-1.2.2.dist-info/RECORD
