Metadata-Version: 2.1
Name: filewiz
Version: 1.2.2
Summary: Quickly rename and move new files into structured folders
License: MIT
Author: Steampunk Wizard
Author-email: filewiz@steampunkwizard.ca
Requires-Python: >=3.11,<4.0
Classifier: License :: OSI Approved :: MIT License
Classifier: Programming Language :: Python :: 3
Classifier: Programming Language :: Python :: 3.11
Requires-Dist: watchdog (>=3.0.0,<4.0.0)
Requires-Dist: wizlib (>=0.9.2,<0.10.0)
